LICENSE.txt
MANIFEST.in
README.md
README.rst
setup.py
easymoney/__init__.py
easymoney/easy_pandas.py
easymoney/money.py
easymoney/options_tools.py
easymoney/pycountry_wrap.py
easymoney/support_tools.py
easymoney.egg-info/PKG-INFO
easymoney.egg-info/SOURCES.txt
easymoney.egg-info/dependency_links.txt
easymoney.egg-info/requires.txt
easymoney.egg-info/top_level.txt
easymoney/sources/__init__.py
easymoney/sources/databases.py
easymoney/sources/databases_new.py
easymoney/sources/ecb_interface.py
easymoney/sources/world_bank_interface.py
easymoney/sources/data/CurrencyRelationshipsDB.csv
easymoney/sources/single_use/__init__.py
easymoney/sources/single_use/currency_relationships.py