Metadata-Version: 1.1
Name: easymoney
Version: 1.5.0
Summary: Data Science Tools for Monetary Information and Conversions.
Home-page: https://github.com/TariqAHassan/EasyMoney.git
Author: Tariq A. Hassan
Author-email: laterallattice@gmail.com
License: BSD
Download-URL: https://github.com/TariqAHassan/EasyMoney/archive/v1.5.0.tar.gz
Keywords: economics,finance,inflation,currency converter,data analysis,data science
Platform: UNKNOWN
Classifier: Development Status :: 5 - Production/Stable
Classifier: Natural Language :: English
Classifier: Intended Audience :: Science/Research
Classifier: Intended Audience :: Financial and Insurance Industry
Classifier: Programming Language :: Python :: 2.7
Classifier: Programming Language :: Python :: 3.3
Classifier: Programming Language :: Python :: 3.4
Classifier: Programming Language :: Python :: 3.5
Classifier: License :: OSI Approved :: BSD License
